libpysat/__init__.py
libpysat/scratch.py
libpysat/clustering/__init__.py
libpysat/clustering/cluster.py
libpysat/examples/__init__.py
libpysat/fileio/__init__.py
libpysat/fileio/header_parser.py
libpysat/fileio/io_json.py
libpysat/fileio/io_moon_minerology_mapper.py
libpysat/fileio/io_multibandimager.py
libpysat/fileio/io_spectral_profiler.py
libpysat/fileio/io_utils.py
libpysat/fileio/io_yaml.py
libpysat/fileio/lookup.py
libpysat/fileio/utils.py
libpysat/plotting/__init__.py
libpysat/plotting/colormaps.py
libpysat/plotting/plots.py
libpysat/regression/__init__.py
libpysat/regression/cv.py
libpysat/regression/pls_cv.py
libpysat/regression/pls_sm.py
libpysat/regression/regression.py
libpysat/regression/sm.py
libpysat/spectral/__init__.py
libpysat/spectral/analytics.py
libpysat/spectral/continuum.py
libpysat/spectral/smoothing.py
libpysat/spectral/spectra.py
libpysat/transform/__init__.py
libpysat/transform/cal_tran.py
libpysat/transform/ccam_denoise.py
libpysat/transform/deriv.py
libpysat/transform/dim_red.py
libpysat/transform/interp.py
libpysat/transform/jade.py
libpysat/transform/lra.py
libpysat/transform/mask.py
libpysat/transform/meancenter.py
libpysat/transform/multiply_vector.py
libpysat/transform/norm.py
libpysat/transform/peak_area.py
libpysat/transform/remove_baseline.py
libpysat/transform/standard_scale.py
libpysat/transform/baseline_code/__init__.py
libpysat/transform/baseline_code/airpls.py
libpysat/transform/baseline_code/als.py
libpysat/transform/baseline_code/ccam_remove_continuum.py
libpysat/transform/baseline_code/common.py
libpysat/transform/baseline_code/dietrich.py
libpysat/transform/baseline_code/fabc.py
libpysat/transform/baseline_code/kajfosz_kwiatek.py
libpysat/transform/baseline_code/mario.py
libpysat/transform/baseline_code/median.py
libpysat/transform/baseline_code/polyfit.py
libpysat/transform/baseline_code/rubberband.py
libpysat/transform/baseline_code/spl_init.py
libpysat-1.3.2.dist-info/METADATA
libpysat-1.3.2.dist-info/RECORD
libpysat-1.3.2.dist-info/WHEEL
libpysat-1.3.2.dist-info/top_level.txt
