Metadata-Version: 2.1
Name: libpysat
Version: 1.3.2
Summary: The Python Spectral Analysis Toolkit (PySAT) for planetary spectral data.
Home-page: https://github.com/USGS-Astrogeology/PySAT
Author: J. Laura
Author-email: jlaura@usgs.gov
License: Unlicense
Platform: UNKNOWN
Classifier: Development Status :: 3 - Alpha
Classifier: Intended Audience :: Developers
Classifier: Programming Language :: Python :: 3.5
Classifier: Programming Language :: Python :: 3.6
Provides-Extra: test
Provides-Extra: dev
Requires-Dist: numpy
Requires-Dist: pandas
Requires-Dist: scipy
Provides-Extra: dev
Provides-Extra: test
Requires-Dist: coverage; extra == 'test'
Requires-Dist: pytest-cov; extra == 'test'
Requires-Dist: coveralls; extra == 'test'
